django_tenancy-0.3.dist-info/DESCRIPTION.rst
django_tenancy-0.3.dist-info/METADATA
django_tenancy-0.3.dist-info/RECORD
django_tenancy-0.3.dist-info/WHEEL
django_tenancy-0.3.dist-info/metadata.json
django_tenancy-0.3.dist-info/top_level.txt
tenancy/__init__.py
tenancy/apps.py
tenancy/compat.py
tenancy/forms.py
tenancy/managers.py
tenancy/middleware.py
tenancy/models.py
tenancy/operations.py
tenancy/settings.py
tenancy/signals.py
tenancy/utils.py
tenancy/views.py
tenancy/auth/__init__.py
tenancy/auth/backends.py
tenancy/management/__init__.py
tenancy/management/commands/__init__.py
tenancy/management/commands/createtenant.py
tenancy/management/commands/createtenantsuperuser.py
tenancy/mutant/__init__.py
tenancy/mutant/models.py
