Metadata-Version: 2.0
Name: django-tenancy
Version: 0.3
Summary: Handle multi-tenancy in Django with no additional global state using schemas.
Home-page: https://github.com/charettes/django-tenancy
Author: Simon Charette
Author-email: charette.s+pypi@gmail.com
License: MIT License
Platform: UNKNOWN
Classifier: Development Status :: 5 - Production/Stable
Classifier: Environment :: Web Environment
Classifier: Framework :: Django
Classifier: Framework :: Django :: 1.8
Classifier: Framework :: Django :: 1.9
Classifier: Framework :: Django :: 1.10
Classifier: Intended Audience :: Developers
Classifier: License :: OSI Approved :: MIT License
Classifier: Operating System :: OS Independent
Classifier: Programming Language :: Python
Classifier: Programming Language :: Python :: 2
Classifier: Programming Language :: Python :: 2.7
Classifier: Programming Language :: Python :: 3
Classifier: Programming Language :: Python :: 3.2
Classifier: Programming Language :: Python :: 3.3
Classifier: Programming Language :: Python :: 3.4
Classifier: Programming Language :: Python :: 3.5
Classifier: Topic :: Software Development :: Libraries :: Python Modules
Requires-Dist: Django (>=1.8)
Provides-Extra: hosts
Requires-Dist: django-hosts; extra == 'hosts'
Provides-Extra: mutant
Requires-Dist: django-mutant (>=0.2.1); extra == 'mutant'
